odoo8_addon_connector_locomotivecms-8.0.0.0.1.99.dev13-py3.8-nspkg.pth
odoo_addons/connector_locomotivecms/README.rst
odoo_addons/connector_locomotivecms/__init__.py
odoo_addons/connector_locomotivecms/__openerp__.py
odoo_addons/connector_locomotivecms/backend.py
odoo_addons/connector_locomotivecms/connector.py
odoo_addons/connector_locomotivecms/related_action.py
odoo_addons/connector_locomotivecms/models/__init__.py
odoo_addons/connector_locomotivecms/models/locomotive_backend.py
odoo_addons/connector_locomotivecms/security/ir.model.access.csv
odoo_addons/connector_locomotivecms/tests/__init__.py
odoo_addons/connector_locomotivecms/tests/common.py
odoo_addons/connector_locomotivecms/unit/__init__.py
odoo_addons/connector_locomotivecms/unit/adapter.py
odoo_addons/connector_locomotivecms/unit/binder.py
odoo_addons/connector_locomotivecms/unit/deleter.py
odoo_addons/connector_locomotivecms/unit/exporter.py
odoo_addons/connector_locomotivecms/views/locomotive_menu.xml
odoo_addons/connector_locomotivecms/views/locomotive_view.xml
odoo8_addon_connector_locomotivecms-8.0.0.0.1.99.dev13.dist-info/METADATA
odoo8_addon_connector_locomotivecms-8.0.0.0.1.99.dev13.dist-info/WHEEL
odoo8_addon_connector_locomotivecms-8.0.0.0.1.99.dev13.dist-info/namespace_packages.txt
odoo8_addon_connector_locomotivecms-8.0.0.0.1.99.dev13.dist-info/top_level.txt
odoo8_addon_connector_locomotivecms-8.0.0.0.1.99.dev13.dist-info/RECORD
