Metadata-Version: 2.1
Name: odoo8-addon-connector-locomotivecms
Version: 8.0.0.0.1.99.dev13
Summary: Connector For Locomotive CMS
Home-page: http://www.akretion.com
Author: Akretion
License: AGPL-3
Platform: UNKNOWN
Classifier: Programming Language :: Python
Classifier: Framework :: Odoo
Classifier: Framework :: Odoo :: 8.0
Classifier: License :: OSI Approved :: GNU Affero General Public License v3
Requires-Python: ~=2.7
Requires-Dist: odoo8-addon-connector-generic
Requires-Dist: odoo (<9.0a,>=8.0a)
